odoo/addons/crm_tag_multi_company_event_crm/README.rst
odoo/addons/crm_tag_multi_company_event_crm/__init__.py
odoo/addons/crm_tag_multi_company_event_crm/__manifest__.py
odoo/addons/crm_tag_multi_company_event_crm/i18n/crm_tag_multi_company_event_crm.pot
odoo/addons/crm_tag_multi_company_event_crm/i18n/it.po
odoo/addons/crm_tag_multi_company_event_crm/models/__init__.py
odoo/addons/crm_tag_multi_company_event_crm/models/event_lead_rule.py
odoo/addons/crm_tag_multi_company_event_crm/readme/CONTRIBUTORS.rst
odoo/addons/crm_tag_multi_company_event_crm/readme/DESCRIPTION.rst
odoo/addons/crm_tag_multi_company_event_crm/static/description/icon.png
odoo/addons/crm_tag_multi_company_event_crm/static/description/index.html
odoo_addon_crm_tag_multi_company_event_crm-16.0.1.0.0.4.dist-info/METADATA
odoo_addon_crm_tag_multi_company_event_crm-16.0.1.0.0.4.dist-info/WHEEL
odoo_addon_crm_tag_multi_company_event_crm-16.0.1.0.0.4.dist-info/top_level.txt
odoo_addon_crm_tag_multi_company_event_crm-16.0.1.0.0.4.dist-info/RECORD
