Metadata-Version: 2.1
Name: odoo-addon-crm_tag_multi_company_event_crm
Version: 16.0.1.0.0.4
Summary: Ensure multi-company check in event lead rules tag ids
Home-page: https://github.com/OCA/multi-company
Author: ForgeFlow,Odoo Community Association (OCA)
Author-email: support@odoo-community.org
License: AGPL-3
Classifier: Programming Language :: Python
Classifier: Framework :: Odoo
Classifier: Framework :: Odoo :: 16.0
Classifier: License :: OSI Approved :: GNU Affero General Public License v3
Requires-Python: >=3.10
Requires-Dist: odoo-addon-crm-tag-multi-company<16.1dev,>=16.0dev
Requires-Dist: odoo<16.1dev,>=16.0a
